submittable_api_client/__init__.py
submittable_api_client/submittable_api_client.py
submittable_api_client-0.6.dist-info/DESCRIPTION.rst
submittable_api_client-0.6.dist-info/METADATA
submittable_api_client-0.6.dist-info/metadata.json
submittable_api_client-0.6.dist-info/RECORD
submittable_api_client-0.6.dist-info/top_level.txt
submittable_api_client-0.6.dist-info/WHEEL
