Metadata-Version: 2.0
Name: submittable-api-client
Version: 0.6
Summary: A client wrapper for the Submittable.com API.
Home-page: https://github.com/shawnr/submittable-api-client
Author: Shawn Rider
Author-email: shawn@shawnrider.com
License: MIT
Download-URL:         https://github.com/shawnr/submittable-api-client/archive/0.6.zip
Keywords: API,REST,Submittable
Platform: UNKNOWN
Requires-Dist: requests (>=2.3.0)
